Phidget22/Async.py
Phidget22/BridgeGain.py
Phidget22/ChannelClass.py
Phidget22/ChannelSubclass.py
Phidget22/CodeInfo.py
Phidget22/ControlMode.py
Phidget22/DataAdapterEndianness.py
Phidget22/DataAdapterFrequency.py
Phidget22/DataAdapterSPIChipSelect.py
Phidget22/DataAdapterSPIMode.py
Phidget22/DataAdapterVoltage.py
Phidget22/DeviceClass.py
Phidget22/DeviceID.py
Phidget22/DriveMode.py
Phidget22/EncoderIOMode.py
Phidget22/Encoding.py
Phidget22/ErrorCode.py
Phidget22/ErrorEventCode.py
Phidget22/FanMode.py
Phidget22/FilterType.py
Phidget22/GPSDate.py
Phidget22/GPSTime.py
Phidget22/HubPortMode.py
Phidget22/IRCodeEncoding.py
Phidget22/IRCodeLength.py
Phidget22/InputMode.py
Phidget22/LCDFont.py
Phidget22/LCDPixelState.py
Phidget22/LCDScreenSize.py
Phidget22/LEDArrayAnimation.py
Phidget22/LEDArrayAnimationType.py
Phidget22/LEDArrayColor.py
Phidget22/LEDArrayColorOrder.py
Phidget22/LEDForwardVoltage.py
Phidget22/Length.py
Phidget22/LogLevel.py
Phidget22/Net.py
Phidget22/PacketErrorCode.py
Phidget22/Phidget.py
Phidget22/PhidgetException.py
Phidget22/PhidgetServer.py
Phidget22/PhidgetServerType.py
Phidget22/PhidgetSupport.py
Phidget22/PortMode.py
Phidget22/PositionType.py
Phidget22/PowerSupply.py
Phidget22/RCServoVoltage.py
Phidget22/RFIDChipset.py
Phidget22/RFIDProtocol.py
Phidget22/RFIDTNF.py
Phidget22/RTDType.py
Phidget22/RTDWireSetup.py
Phidget22/SPLRange.py
Phidget22/SpatialAlgorithm.py
Phidget22/SpatialEulerAngles.py
Phidget22/SpatialPrecision.py
Phidget22/SpatialQuaternion.py
Phidget22/StepperControlMode.py
Phidget22/ThermocoupleType.py
Phidget22/Unit.py
Phidget22/UnitInfo.py
Phidget22/VoltageOutputRange.py
Phidget22/VoltageRange.py
Phidget22/VoltageRatioSensorType.py
Phidget22/VoltageSensorType.py
Phidget22/__init__.py
Phidget22/Devices/Accelerometer.py
Phidget22/Devices/BLDCMotor.py
Phidget22/Devices/CapacitiveTouch.py
Phidget22/Devices/CurrentInput.py
Phidget22/Devices/DCMotor.py
Phidget22/Devices/Dictionary.py
Phidget22/Devices/DigitalInput.py
phidget22-1.23.20251006.dist-info/LICENSE
phidget22-1.23.20251006.dist-info/METADATA
phidget22-1.23.20251006.dist-info/WHEEL
phidget22-1.23.20251006.dist-info/top_level.txt
phidget22-1.23.20251006.dist-info/RECORD
