Metadata-Version: 2.1
Name: phidget22
Version: 1.23.20251006
Summary: Phidget22 Python wrapper library
Home-page: http://www.phidgets.com
Author: Phidgets Inc
Author-email: support@phidgets.com
License: BSD-3-Clause
Platform: UNKNOWN
Classifier: Programming Language :: Python :: 2
Classifier: Programming Language :: Python :: 3
Classifier: License :: OSI Approved :: BSD License
Classifier: Operating System :: OS Independent
